cloud_radar/__init__.py
cloud_radar/cf/__init__.py
cloud_radar/cf/e2e/__init__.py
cloud_radar/cf/e2e/_stack.py
cloud_radar/cf/unit/__init__.py
cloud_radar/cf/unit/_condition.py
cloud_radar/cf/unit/_hooks.py
cloud_radar/cf/unit/_output.py
cloud_radar/cf/unit/_parameter.py
cloud_radar/cf/unit/_resource.py
cloud_radar/cf/unit/_stack.py
cloud_radar/cf/unit/_template.py
cloud_radar/cf/unit/functions.py
cloud_radar/cf/unit/test__template.py
cloud_radar-0.15.0.dist-info/LICENSE.txt
cloud_radar-0.15.0.dist-info/METADATA
cloud_radar-0.15.0.dist-info/WHEEL
cloud_radar-0.15.0.dist-info/RECORD
