Metadata-Version: 2.3
Name: cloud-radar
Version: 0.15.0
Summary: Run functional tests on cloudformation stacks.
License: Apache-2.0
Keywords: aws,cloudformation,cloud-radar,testing,taskcat,cloud,radar
Author: Levi Blaney
Author-email: shadycuz+dev@gmail.com
Requires-Python: >=3.9,<4.0
Classifier: Development Status :: 2 - Pre-Alpha
Classifier: License :: OSI Approved :: Apache Software License
Classifier: Operating System :: OS Independent
Classifier: Programming Language :: Python :: 3
Classifier: Programming Language :: Python :: 3.9
Classifier: Programming Language :: Python :: 3.10
Classifier: Programming Language :: Python :: 3.11
Classifier: Programming Language :: Python :: 3.12
Classifier: Programming Language :: Python :: 3.13
Classifier: Topic :: Software Development :: Libraries
Classifier: Topic :: Software Development :: Testing
Requires-Dist: botocore (>=1.35.36,<2.0.0)
Requires-Dist: cfn-flip (>=1.3.0,<2.0.0)
Requires-Dist: taskcat (>=0.9.41,<1.0.0)
Project-URL: Changelog, https://github.com/DontShaveTheYak/cloud-radar/releases
Project-URL: Issues, https://github.com/DontShaveTheYak/cloud-radar/issues
Project-URL: Repository, https://github.com/DontShaveTheYak/cloud-radar
